s2stac/__init__.py
s2stac/_asset.py
s2stac/_aux_data.py
s2stac/_catalog.py
s2stac/_img_data.py
s2stac/_mtd_tl.py
s2stac/_preview.py
s2stac/_qi_data.py
s2stac/_srtm.py
s2stac/_stacify.py
s2stac-0.1.3.dist-info/WHEEL
s2stac-0.1.3.dist-info/METADATA
s2stac-0.1.3.dist-info/LICENSE
s2stac-0.1.3.dist-info/RECORD
